{
  "status": "success",
  "message": "Skan 7 profili zakończony pomyślnie",
  "lastScan": {
    "timestamp": "2026-04-06T10:48:31Z",
    "duration_seconds": 155,
    "profiles_scanned": 7,
    "total_listings": 421,
    "new_listings": 0,
    "price_changes": 170
  },
  "nextScan": {
    "scheduled": "2026-04-07T07:00:00Z",
    "in_seconds": 72688
  },
  "profiles": {
    "wszystkie_pokoje": {
      "label": "Wszystkie pokoje w Lublinie",
      "count": 353,
      "crosscheck": "passed"
    },
    "pokojewlublinie": {
      "label": "pokojewlublinie",
      "count": 1,
      "crosscheck": "passed"
    },
    "poqui": {
      "label": "poqui",
      "count": 10,
      "crosscheck": "passed"
    },
    "artymiuk": {
      "label": "artymiuk",
      "count": 1,
      "crosscheck": "passed"
    },
    "dawny_patron": {
      "label": "dawny patron",
      "count": 2,
      "crosscheck": "passed"
    },
    "mzuri": {
      "label": "mzuri",
      "count": 54,
      "crosscheck": "passed"
    },
    "villahome": {
      "label": "villahome",
      "count": 0,
      "crosscheck": "passed"
    }
  }
}